pypyfupmcp/__init__.py
pypyfupmcp-0.1.0.dist-info/METADATA
pypyfupmcp-0.1.0.dist-info/WHEEL
pypyfupmcp-0.1.0.dist-info/entry_points.txt
pypyfupmcp-0.1.0.dist-info/RECORD
