Metadata-Version: 2.4
Name: pypyfupmcp
Version: 0.1.0
Summary: Add your description here
Author-email: datafu <24384760+datafu@users.noreply.github.com>
Requires-Python: >=3.13
Requires-Dist: mcp[cli]>=1.9.3
